CHANGELOG.rst
MANIFEST.in
README.rst
setup.py
scrutinizer/__init__.py
scrutinizer/ocular/__init__.py
scrutinizer/ocular/app.py
scrutinizer/ocular/coverage_parser.py
scrutinizer/ocular/repository_introspector.py
scrutinizer/ocular/uploader.py
scrutinizer_ocular.egg-info/PKG-INFO
scrutinizer_ocular.egg-info/SOURCES.txt
scrutinizer_ocular.egg-info/dependency_links.txt
scrutinizer_ocular.egg-info/entry_points.txt
scrutinizer_ocular.egg-info/requires.txt
scrutinizer_ocular.egg-info/top_level.txt