Metadata-Version: 1.1
Name: scrutinizer-ocular
Version: 1.0.3
Summary: Reports Python code coverage data to scrutinizer-ci.com
Home-page: http://github.com/scrutinizer-ci/ocular.py
Author: Scrutinizer
Author-email: support@scrutinizer-ci.com
License: MIT
Platform: UNKNOWN
Classifier: Development Status :: 5 - Production/Stable
Classifier: Topic :: Software Development :: Testing
Classifier: Intended Audience :: Developers
Classifier: License :: OSI Approved :: MIT License
Classifier: Operating System :: OS Independent
Classifier: Programming Language :: Python
Classifier: Programming Language :: Python :: 2.6
Classifier: Programming Language :: Python :: 2.7
Classifier: Programming Language :: Python :: 3.2
Classifier: Programming Language :: Python :: 3.3
Classifier: Programming Language :: Python :: Implementation :: PyPy
Classifier: Programming Language :: Python :: Implementation :: CPython
